python_postgres/__init__.py
python_postgres/_client.py
python_postgres/_operations.py
python_postgres/_transactions.py
python_postgres/types.py
python_postgres-0.0.21.dist-info/METADATA
python_postgres-0.0.21.dist-info/WHEEL
python_postgres-0.0.21.dist-info/licenses/LICENSE
python_postgres-0.0.21.dist-info/RECORD
