Metadata-Version: 2.4
Name: python-postgres
Version: 0.0.21
Summary: Combine the flexibility and power of PostgreSQL with the convenience of ORMs.
Project-URL: Documentation, https://vinzenzklass.github.io/python-postgres
Project-URL: Repository, https://github.com/VinzenzKlass/python-postgres
Project-URL: Psycopg Docs, https://www.psycopg.org/psycopg3/docs/index.html
Author-email: Vinzenz Klass <vinzenz.klass@valantic.com>
License-File: LICENSE
Keywords: PostgreSQL,postgres,psql,python-postgres
Requires-Python: >=3.13
Requires-Dist: psycopg[pool]>=3.2.6
Requires-Dist: pydantic>=2.10.0
Provides-Extra: binary
Requires-Dist: psycopg[binary]>=3.2.0; extra == 'binary'
Provides-Extra: c
Requires-Dist: psycopg[c]>=3.2.0; extra == 'c'
